pv60hz/__init__.py
pv60hz/exceptions.py
pv60hz/common/__init__.py
pv60hz/common/utils.py
pv60hz/loader/__init__.py
pv60hz/loader/gfs.py
pv60hz/loader/gfs_variable.py
pv60hz/preprocessor/__init__.py
pv60hz/preprocessor/preprocess.py
pv60hz/simulator/__init__.py
pv60hz/simulator/simulate.py
pv60hz/tests/__init__.py
pv60hz/tests/common/__init__.py
pv60hz/tests/common/test_utils.py
pv60hz/tests/loader/__init__.py
pv60hz/tests/loader/test_gfs.py
pv60hz/tests/preprocessor/__init__.py
pv60hz/tests/preprocessor/test_preprocessor.py
pv60hz/tests/simulator/__init__.py
pv60hz/tests/simulator/test_simulate.py
pv60hz-0.0.4.dist-info/LICENSE
pv60hz-0.0.4.dist-info/METADATA
pv60hz-0.0.4.dist-info/WHEEL
pv60hz-0.0.4.dist-info/top_level.txt
pv60hz-0.0.4.dist-info/RECORD
