Metadata-Version: 2.1
Name: pv60hz
Version: 0.0.4
Summary: PV Forecast simulation
Home-page: https://github.com/60hz-io/pv60hz
Author: JiHyeong Seo
Author-email: it-admins@60hz.io
License: UNKNOWN
Platform: UNKNOWN
Classifier: Programming Language :: Python :: 3
Classifier: Programming Language :: Python :: 3.6
Classifier: License :: OSI Approved :: BSD License
Classifier: Operating System :: OS Independent
Classifier: Intended Audience :: Science/Research
Requires-Python: >=3.6
Requires-Dist: pandas
Requires-Dist: dataclasses
Requires-Dist: arrow
Requires-Dist: xarray
Requires-Dist: bs4
Requires-Dist: tqdm
Requires-Dist: pvlib
